typeshit/__init__.py
typeshit/main.py
typeshit-0.2.2.dist-info/LICENSE
typeshit-0.2.2.dist-info/METADATA
typeshit-0.2.2.dist-info/WHEEL
typeshit-0.2.2.dist-info/entry_points.txt
typeshit-0.2.2.dist-info/top_level.txt
typeshit-0.2.2.dist-info/RECORD
