Metadata-Version: 2.1
Name: typeshit
Version: 0.2.2
Summary: wrong lang? you got typeshit
Home-page: https://github.com/Ebrahim-Ramadan/wetype-tool
Author: Ebrahim Ramadan
Author-email: ramadanebrahim791@gmail.com
Classifier: Programming Language :: Python :: 3
Classifier: License :: OSI Approved :: MIT License
Classifier: Operating System :: OS Independent
Classifier: Topic :: Software Development
License-File: LICENSE
Requires-Dist: pynput
Requires-Dist: langdetect
